{
  "$schema": "https://elio.dev/demo-time.schema.json",
  "title": "5 - Close",
  "description": "",
  "demos": [
    {
      "title": "Dapr Website",
      "icons": {
        "start": "note",
        "end": "pass-filled"
      },
      "steps": [
        {
          "action": "executeVSCodeCommand",
          "command": "workbench.action.terminal.killAll"
        },
        {
          "action": "executeVSCodeCommand",
          "command": "workbench.action.closeSidebar"
        },
        {
          "action": "openSlide",
          "path": ".demo/slides/5-close/dapr-website.md"
        }
      ]
    },
    {
      "title": "Dapr University",
      "icons": {
        "start": "note",
        "end": "pass-filled"
      },
      "steps": [
        {
          "action": "openSlide",
          "path": ".demo/slides/5-close/dapr-university.md"
        }
      ]
    },
    {
      "title": "Dapr Workflow Composer",
      "icons": {
        "start": "note",
        "end": "pass-filled"
      },
      "steps": [
        {
          "action": "openSlide",
          "path": ".demo/slides/5-close/dapr-workflow-composer.md"
        }
      ]
    },
    // {
    //   "title": "Dapr Resources",
    //   "icons": {
    //     "start": "note",
    //     "end": "pass-filled"
    //   },
    //   "steps": [
    //     {
    //       "action": "openSlide",
    //       "path": ".demo/slides/5-close/dapr-resources.md"
    //     }
    //   ]
    // },
    {
      "title": "Workflow & Resiliency Repo",
      "icons": {
        "start": "note",
        "end": "pass-filled"
      },
      "steps": [
        {
          "action": "openSlide",
          "path": ".demo/slides/5-close/dapr-workflow-repo.md"
        }
      ]
    },
    {
      "title": "Claim the supporter badge",
      "icons": {
        "start": "note",
        "end": "pass-filled"
      },
      "steps": [
        {
          "action": "openSlide",
          "path": ".demo/slides/5-close/supporter-badge.md"
        }
      ]
    }
  ]
}